{
	"Other": [
	{
		"id": 1,
		"title": "",
		"sub_title": "",
		"content": "",
		"img": ""
	},{
		"id": 2,
		"title": "",
		"sub_title": "",
		"content": "",
		"second_title": "",
		"second_content": "",
		"img": ""
	},{
		"id": 3,
		"title": "",
		"sub_title": "",
		"content": "",
		"second_title": "",
		"second_content": "",
		"img": ""
	},{
		"id": 4,
		"title": "",
		"sub_title": "",
		"content": "",
		"second_title": "",
		"second_content": "",
		"third_title": "",
		"third_content": "",
		"fourth_title": "",
		"fourth_content": "",
		"fifth_title": "",
		"fifth_content": "",
		"img": ""
	},{
		"id": 5,
		"title": "",
		"sub_title": "",
		"content": "",
		"third_title": "",
		"third_content": "",
		"fourth_title": "",
		"fourth_content": "",
		"fifth_title": "",
		"fifth_content": "",
		"img": ""
	}]

}
